fntlib/__init__.py
fntlib/main.py
fntlib/utils.py
fntlib-1.0.0.dist-info/LICENSE.rst
fntlib-1.0.0.dist-info/METADATA
fntlib-1.0.0.dist-info/WHEEL
fntlib-1.0.0.dist-info/top_level.txt
fntlib-1.0.0.dist-info/RECORD
